sim/PipelineProcessor.v
// ============================================================================
// 5-Stage Pipelined RISC Processor with Hazard Handling
// Assignment 3: Computer Organization & Architecture
// ============================================================================

// ============================================================================
// 1. MAIN PROCESSOR MODULE
// ============================================================================
module PipelineProcessor (
    input clk,
    input reset
);

    // ===== Pipeline Signals =====

    // IF/ID Pipeline Register
    reg [31:0] IFID_PC;
    reg [31:0] IFID_Instruction;

    // ID/EX Pipeline Register
    reg [31:0] IDEX_RegData1;
    reg [31:0] IDEX_RegData2;
    reg [31:0] IDEX_SignExtImm;
    reg [4:0]  IDEX_Rd;
    reg [4:0]  IDEX_Rs1;
    reg [4:0]  IDEX_Rs2;
    reg [2:0]  IDEX_ALUOp;
    reg        IDEX_RegWrite;
    reg        IDEX_MemRead;
    reg        IDEX_MemWrite;

    // EX/MEM Pipeline Register
    reg [31:0] EXMEM_ALUResult;
    reg [31:0] EXMEM_WriteData;
    reg [4:0]  EXMEM_Rd;
    reg        EXMEM_RegWrite;
    reg        EXMEM_MemRead;
    reg        EXMEM_MemWrite;

    // MEM/WB Pipeline Register
    reg [31:0] MEMWB_MemReadData;
    reg [31:0] MEMWB_ALUResult;
    reg [4:0]  MEMWB_Rd;
    reg        MEMWB_RegWrite;

    // ===== Control Signals =====
    wire [1:0] ForwardA, ForwardB;
    wire       Stall;
    wire       PCWrite;
    wire       IFIDWrite;

    // ===== Program Counter =====
    reg [31:0] PC;
    wire [31:0] PC_next;
    wire [31:0] PC_plus_4;

    // ===== Memories =====
    reg [31:0] InstMem [0:1023];  // Instruction Memory
    reg [31:0] DataMem [0:1023];  // Data Memory

    // ===== Register File =====
    reg [31:0] RegFile [0:31];

    // ===== Fetch Stage (IF) =====
    wire [31:0] Instruction;

    assign PC_plus_4 = PC + 32'd4;
    assign PC_next = Stall ? PC : PC_plus_4;
    assign Instruction = InstMem[PC[9:0]];

    always @(posedge clk or posedge reset) begin
        if (reset)
            PC <= 32'd0;
        else if (PCWrite)
            PC <= PC_next;
    end

    // ===== Decode Stage (ID) =====
    wire [6:0]  opcode = IFID_Instruction[6:0];
    wire [2:0]  funct3 = IFID_Instruction[14:12];
    wire [6:0]  funct7 = IFID_Instruction[31:25];
    wire [4:0]  rs1_addr = IFID_Instruction[19:15];
    wire [4:0]  rs2_addr = IFID_Instruction[24:20];
    wire [4:0]  rd_addr = IFID_Instruction[11:7];
    wire [31:0] imm_signed = {{20{IFID_Instruction[31]}}, IFID_Instruction[31:20]};

    wire [31:0] RegData1 = RegFile[rs1_addr];
    wire [31:0] RegData2 = RegFile[rs2_addr];

    wire RegWrite_ID, MemRead_ID, MemWrite_ID;
    wire [2:0] ALUOp_ID;

    ControlUnit control_unit (
        .opcode(opcode),
        .RegWrite(RegWrite_ID),
        .MemRead(MemRead_ID),
        .MemWrite(MemWrite_ID),
        .ALUOp(ALUOp_ID)
    );

    // ===== Execute Stage (EX) =====
    wire [31:0] ALUInputA, ALUInputB;
    wire [31:0] ALUResult;

    assign ALUInputA = (ForwardA == 2'b10) ? EXMEM_ALUResult :
                       (ForwardA == 2'b01) ? MEMWB_ALUResult :
                       IDEX_RegData1;

    assign ALUInputB = (ForwardB == 2'b10) ? EXMEM_ALUResult :
                       (ForwardB == 2'b01) ? MEMWB_ALUResult :
                       IDEX_RegData2;

    ALU alu (
        .InputA(ALUInputA),
        .InputB(ALUInputB),
        .ALUOp(IDEX_ALUOp),
        .Result(ALUResult)
    );

    // ===== Memory Stage (MEM) =====
    wire [31:0] MemReadData;

    assign MemReadData = DataMem[EXMEM_ALUResult[9:0]];

    always @(posedge clk) begin
        if (EXMEM_MemWrite)
            DataMem[EXMEM_ALUResult[9:0]] <= EXMEM_WriteData;
    end

    // ===== Write-Back Stage (WB) =====
    wire [31:0] WriteData;

    assign WriteData = MEMWB_RegWrite ? 
                      (MEMWB_MemReadData != 0 ? MEMWB_MemReadData : MEMWB_ALUResult) :
                      32'd0;

    always @(posedge clk or posedge reset) begin
        if (reset) begin
            RegFile[0] <= 32'd0;
            RegFile[1] <= 32'd0;
            RegFile[2] <= 32'd5;   // R2 = 5
            RegFile[3] <= 32'd3;   // R3 = 3
            RegFile[4] <= 32'd0;
            RegFile[5] <= 32'd2;   // R5 = 2
            RegFile[6] <= 32'd0;
            RegFile[7] <= 32'd1;   // R7 = 1
        end else if (MEMWB_RegWrite && MEMWB_Rd != 0) begin
            RegFile[MEMWB_Rd] <= WriteData;
        end
    end

    // ===== Hazard Detection Unit =====
    HazardDetectionUnit hazard_unit (
        .ID_EX_MemRead(IDEX_MemRead),
        .ID_EX_Rd(IDEX_Rd),
        .IF_ID_Rs1(rs1_addr),
        .IF_ID_Rs2(rs2_addr),
        .Stall(Stall),
        .PCWrite(PCWrite),
        .IFIDWrite(IFIDWrite)
    );

    // ===== Forwarding Unit =====
    ForwardingUnit forwarding_unit (
        .EX_MEM_RegWrite(EXMEM_RegWrite),
        .EX_MEM_Rd(EXMEM_Rd),
        .MEM_WB_RegWrite(MEMWB_RegWrite),
        .MEM_WB_Rd(MEMWB_Rd),
        .ID_EX_Rs1(IDEX_Rs1),
        .ID_EX_Rs2(IDEX_Rs2),
        .ForwardA(ForwardA),
        .ForwardB(ForwardB)
    );

    // ===== Pipeline Register Updates =====

    // IF/ID Register
    always @(posedge clk or posedge reset) begin
        if (reset) begin
            IFID_PC <= 32'd0;
            IFID_Instruction <= 32'd0;
        end else if (IFIDWrite) begin
            IFID_PC <= PC;
            IFID_Instruction <= Instruction;
        end
    end

    // ID/EX Register
    always @(posedge clk or posedge reset) begin
        if (reset) begin
            IDEX_RegData1 <= 32'd0;
            IDEX_RegData2 <= 32'd0;
            IDEX_SignExtImm <= 32'd0;
            IDEX_Rd <= 5'd0;
            IDEX_Rs1 <= 5'd0;
            IDEX_Rs2 <= 5'd0;
            IDEX_ALUOp <= 3'd0;
            IDEX_RegWrite <= 1'b0;
            IDEX_MemRead <= 1'b0;
            IDEX_MemWrite <= 1'b0;
        end else if (!Stall) begin
            IDEX_RegData1 <= RegData1;
            IDEX_RegData2 <= RegData2;
            IDEX_SignExtImm <= imm_signed;
            IDEX_Rd <= rd_addr;
            IDEX_Rs1 <= rs1_addr;
            IDEX_Rs2 <= rs2_addr;
            IDEX_ALUOp <= ALUOp_ID;
            IDEX_RegWrite <= RegWrite_ID;
            IDEX_MemRead <= MemRead_ID;
            IDEX_MemWrite <= MemWrite_ID;
        end else begin
            // Insert NOP (bubble) when stall occurs
            IDEX_RegWrite <= 1'b0;
            IDEX_MemRead <= 1'b0;
            IDEX_MemWrite <= 1'b0;
        end
    end

    // EX/MEM Register
    always @(posedge clk or posedge reset) begin
        if (reset) begin
            EXMEM_ALUResult <= 32'd0;
            EXMEM_WriteData <= 32'd0;
            EXMEM_Rd <= 5'd0;
            EXMEM_RegWrite <= 1'b0;
            EXMEM_MemRead <= 1'b0;
            EXMEM_MemWrite <= 1'b0;
        end else begin
            EXMEM_ALUResult <= ALUResult;
            EXMEM_WriteData <= ALUInputB;
            EXMEM_Rd <= IDEX_Rd;
            EXMEM_RegWrite <= IDEX_RegWrite;
            EXMEM_MemRead <= IDEX_MemRead;
            EXMEM_MemWrite <= IDEX_MemWrite;
        end
    end

    // MEM/WB Register
    always @(posedge clk or posedge reset) begin
        if (reset) begin
            MEMWB_MemReadData <= 32'd0;
            MEMWB_ALUResult <= 32'd0;
            MEMWB_Rd <= 5'd0;
            MEMWB_RegWrite <= 1'b0;
        end else begin
            MEMWB_MemReadData <= MemReadData;
            MEMWB_ALUResult <= EXMEM_ALUResult;
            MEMWB_Rd <= EXMEM_Rd;
            MEMWB_RegWrite <= EXMEM_RegWrite;
        end
    end

    // ===== Initialize Instruction Memory =====
    initial begin
        // Sample 10-instruction program
        InstMem[0]  = 32'h00a28533;  // ADD R1, R2, R3
        InstMem[1]  = 32'h40328733;  // SUB R4, R1, R5
        InstMem[2]  = 32'h00726833;  // AND R6, R1, R7
        InstMem[3]  = 32'h00428933;  // OR R8, R1, R4
        InstMem[4]  = 32'h00148483;  // LOAD R9, 0(R1)
        InstMem[5]  = 32'h00948533;  // ADD R10, R9, R2
        InstMem[6]  = 32'h00228063;  // BEQ R1, R2, 8
        InstMem[7]  = 32'h40318b33;  // SUB R11, R3, R4
        InstMem[8]  = 32'h00a52a23;  // STORE R10, 0(R2)
        InstMem[9]  = 32'h00858633;  // ADD R12, R11, R8
    end

    // ===== Initialize Data Memory =====
    initial begin
        DataMem[0] = 32'h00000010;  // Sample data at address 0
    end

endmodule

// ============================================================================
// 2. CONTROL UNIT
// ============================================================================
module ControlUnit (
    input [6:0] opcode,
    output reg RegWrite,
    output reg MemRead,
    output reg MemWrite,
    output reg [2:0] ALUOp
);

    always @(*) begin
        case (opcode)
            7'b0110011: begin  // R-type (ADD, SUB, AND, OR, XOR)
                RegWrite = 1'b1;
                MemRead = 1'b0;
                MemWrite = 1'b0;
                ALUOp = 3'b000;  // ADD by default
            end
            7'b0010011: begin  // I-type (ADDI, etc.)
                RegWrite = 1'b1;
                MemRead = 1'b0;
                MemWrite = 1'b0;
                ALUOp = 3'b000;  // ADD
            end
            7'b0000011: begin  // LOAD
                RegWrite = 1'b1;
                MemRead = 1'b1;
                MemWrite = 1'b0;
                ALUOp = 3'b000;  // ADD (for address)
            end
            7'b0100011: begin  // STORE
                RegWrite = 1'b0;
                MemRead = 1'b0;
                MemWrite = 1'b1;
                ALUOp = 3'b000;  // ADD (for address)
            end
            7'b1100011: begin  // BRANCH
                RegWrite = 1'b0;
                MemRead = 1'b0;
                MemWrite = 1'b0;
                ALUOp = 3'b001;  // SUB (for comparison)
            end
            default: begin
                RegWrite = 1'b0;
                MemRead = 1'b0;
                MemWrite = 1'b0;
                ALUOp = 3'b000;
            end
        endcase
    end

endmodule

// ============================================================================
// 3. ALU (Arithmetic Logic Unit)
// ============================================================================
module ALU (
    input [31:0] InputA,
    input [31:0] InputB,
    input [2:0]  ALUOp,
    output reg [31:0] Result
);

    always @(*) begin
        case (ALUOp)
            3'b000: Result = InputA + InputB;           // ADD
            3'b001: Result = InputA - InputB;           // SUB
            3'b010: Result = InputA & InputB;           // AND
            3'b011: Result = InputA | InputB;           // OR
            3'b100: Result = InputA ^ InputB;           // XOR
            3'b101: Result = InputA << InputB[4:0];     // SLL
            3'b110: Result = InputA >> InputB[4:0];     // SRL
            3'b111: Result = InputA ^ InputB;           // XOR (default)
            default: Result = 32'd0;
        endcase
    end

endmodule

// ============================================================================
// 4. HAZARD DETECTION UNIT
// ============================================================================
module HazardDetectionUnit (
    input        ID_EX_MemRead,
    input [4:0]  ID_EX_Rd,
    input [4:0]  IF_ID_Rs1,
    input [4:0]  IF_ID_Rs2,
    output reg   Stall,
    output wire  PCWrite,
    output wire  IFIDWrite
);

    always @(*) begin
        if (ID_EX_MemRead && ((ID_EX_Rd == IF_ID_Rs1) || (ID_EX_Rd == IF_ID_Rs2))) begin
            Stall = 1'b1;
        end else begin
            Stall = 1'b0;
        end
    end

    assign PCWrite = !Stall;
    assign IFIDWrite = !Stall;

endmodule

// ============================================================================
// 5. FORWARDING UNIT
// ============================================================================
module ForwardingUnit (
    input        EX_MEM_RegWrite,
    input [4:0]  EX_MEM_Rd,
    input        MEM_WB_RegWrite,
    input [4:0]  MEM_WB_Rd,
    input [4:0]  ID_EX_Rs1,
    input [4:0]  ID_EX_Rs2,
    output reg [1:0] ForwardA,
    output reg [1:0] ForwardB
);

    always @(*) begin
        // ForwardA logic for ALU operand A
        if (EX_MEM_RegWrite && (EX_MEM_Rd != 5'd0) && (EX_MEM_Rd == ID_EX_Rs1)) begin
            ForwardA = 2'b10;  // From EX/MEM
        end else if (MEM_WB_RegWrite && (MEM_WB_Rd != 5'd0) && (MEM_WB_Rd == ID_EX_Rs1)) begin
            ForwardA = 2'b01;  // From MEM/WB
        end else begin
            ForwardA = 2'b00;  // No forwarding
        end

        // ForwardB logic for ALU operand B
        if (EX_MEM_RegWrite && (EX_MEM_Rd != 5'd0) && (EX_MEM_Rd == ID_EX_Rs2)) begin
            ForwardB = 2'b10;  // From EX/MEM
        end else if (MEM_WB_RegWrite && (MEM_WB_Rd != 5'd0) && (MEM_WB_Rd == ID_EX_Rs2)) begin
            ForwardB = 2'b01;  // From MEM/WB
        end else begin
            ForwardB = 2'b00;  // No forwarding
        end
    end

endmodule

sim/testbench.sv
// ============================================================================
// TESTBENCH: 5-Stage Pipelined RISC Processor
// ============================================================================

`timescale 1ns/1ps

module testbench;
    reg clk;
    reg reset;

    // Instantiate processor
    PipelineProcessor processor (
        .clk(clk),
        .reset(reset)
    );

    // ===== Clock Generation =====
    initial begin
        clk = 0;
        forever #5 clk = ~clk;  // 10ns clock period (100 MHz)
    end

    // ===== Simulation Control =====
    initial begin
        // Enable waveform dumping for GTKWave or ModelSim
        $dumpfile("pipeline_simulation.vcd");
        $dumpvars(0, testbench);

        // Reset processor
        reset = 1'b1;
        #10;
        reset = 1'b0;

        // Run simulation for 200 cycles (to see stalls, forwarding, etc.)
        #2000;

        // Print results
        $display("\n========================================");
        $display("SIMULATION COMPLETE");
        $display("========================================\n");

        // Display final register values
        $display("Final Register Values:");
        $display("R1  = %h", processor.RegFile[1]);
        $display("R2  = %h", processor.RegFile[2]);
        $display("R3  = %h", processor.RegFile[3]);
        $display("R4  = %h", processor.RegFile[4]);
        $display("R5  = %h", processor.RegFile[5]);
        $display("R6  = %h", processor.RegFile[6]);
        $display("R7  = %h", processor.RegFile[7]);
        $display("R8  = %h", processor.RegFile[8]);
        $display("R9  = %h", processor.RegFile[9]);
        $display("R10 = %h", processor.RegFile[10]);
        $display("R11 = %h", processor.RegFile[11]);
        $display("R12 = %h", processor.RegFile[12]);

        $display("\nFinal Data Memory Values:");
        $display("Mem[0] = %h", processor.DataMem[0]);
        $display("Mem[1] = %h", processor.DataMem[1]);

        $finish;
    end

    // ===== Per-Cycle Monitoring =====
    integer cycle_count = 0;

    always @(posedge clk) begin
        cycle_count = cycle_count + 1;

        // Print pipeline state every cycle
        if (cycle_count > 1 && cycle_count < 20) begin  // First 20 cycles
            $display("\nCycle %0d:", cycle_count);
            $display("  PC = %h", processor.PC);
            $display("  Stall = %b", processor.Stall);
            $display("  IF/ID.Inst = %h", processor.IFID_Instruction);
            $display("  ID/EX.Rd = %0d", processor.IDEX_Rd);
            $display("  EX/MEM.ALUResult = %h", processor.EXMEM_ALUResult);
            $display("  MEM/WB.Rd = %0d", processor.MEMWB_Rd);
            $display("  ForwardA = %b, ForwardB = %b", processor.ForwardA, processor.ForwardB);
        end
    end

endmodule

sim/pipeline_simulation.vcd
$date
	Thu Nov 13 20:00:44 2025
$end
$version
	Icarus Verilog
$end
$timescale
	1ps
$end
$scope module testbench $end
$var reg 1 ! clk $end
$var reg 1 " reset $end
$var integer 32 # cycle_count [31:0] $end
$scope module processor $end
$var wire 32 $ Instruction [31:0] $end
$var wire 32 % MemReadData [31:0] $end
$var wire 32 & RegData1 [31:0] $end
$var wire 32 ' RegData2 [31:0] $end
$var wire 1 ! clk $end
$var wire 1 " reset $end
$var wire 5 ( rs2_addr [4:0] $end
$var wire 5 ) rs1_addr [4:0] $end
$var wire 5 * rd_addr [4:0] $end
$var wire 7 + opcode [6:0] $end
$var wire 32 , imm_signed [31:0] $end
$var wire 7 - funct7 [6:0] $end
$var wire 3 . funct3 [2:0] $end
$var wire 32 / WriteData [31:0] $end
$var wire 1 0 Stall $end
$var wire 1 1 RegWrite_ID $end
$var wire 32 2 PC_plus_4 [31:0] $end
$var wire 32 3 PC_next [31:0] $end
$var wire 1 4 PCWrite $end
$var wire 1 5 MemWrite_ID $end
$var wire 1 6 MemRead_ID $end
$var wire 1 7 IFIDWrite $end
$var wire 2 8 ForwardB [1:0] $end
$var wire 2 9 ForwardA [1:0] $end
$var wire 32 : ALUResult [31:0] $end
$var wire 3 ; ALUOp_ID [2:0] $end
$var wire 32 < ALUInputB [31:0] $end
$var wire 32 = ALUInputA [31:0] $end
$var reg 32 > EXMEM_ALUResult [31:0] $end
$var reg 1 ? EXMEM_MemRead $end
$var reg 1 @ EXMEM_MemWrite $end
$var reg 5 A EXMEM_Rd [4:0] $end
$var reg 1 B EXMEM_RegWrite $end
$var reg 32 C EXMEM_WriteData [31:0] $end
$var reg 3 D IDEX_ALUOp [2:0] $end
$var reg 1 E IDEX_MemRead $end
$var reg 1 F IDEX_MemWrite $end
$var reg 5 G IDEX_Rd [4:0] $end
$var reg 32 H IDEX_RegData1 [31:0] $end
$var reg 32 I IDEX_RegData2 [31:0] $end
$var reg 1 J IDEX_RegWrite $end
$var reg 5 K IDEX_Rs1 [4:0] $end
$var reg 5 L IDEX_Rs2 [4:0] $end
$var reg 32 M IDEX_SignExtImm [31:0] $end
$var reg 32 N IFID_Instruction [31:0] $end
$var reg 32 O IFID_PC [31:0] $end
$var reg 32 P MEMWB_ALUResult [31:0] $end
$var reg 32 Q MEMWB_MemReadData [31:0] $end
$var reg 5 R MEMWB_Rd [4:0] $end
$var reg 1 S MEMWB_RegWrite $end
$var reg 32 T PC [31:0] $end
$scope module alu $end
$var wire 3 U ALUOp [2:0] $end
$var wire 32 V InputA [31:0] $end
$var wire 32 W InputB [31:0] $end
$var reg 32 X Result [31:0] $end
$upscope $end
$scope module control_unit $end
$var wire 7 Y opcode [6:0] $end
$var reg 3 Z ALUOp [2:0] $end
$var reg 1 6 MemRead $end
$var reg 1 5 MemWrite $end
$var reg 1 1 RegWrite $end
$upscope $end
$scope module forwarding_unit $end
$var wire 5 [ EX_MEM_Rd [4:0] $end
$var wire 1 B EX_MEM_RegWrite $end
$var wire 5 \ ID_EX_Rs1 [4:0] $end
$var wire 5 ] ID_EX_Rs2 [4:0] $end
$var wire 5 ^ MEM_WB_Rd [4:0] $end
$var wire 1 S MEM_WB_RegWrite $end
$var reg 2 _ ForwardA [1:0] $end
$var reg 2 ` ForwardB [1:0] $end
$upscope $end
$scope module hazard_unit $end
$var wire 1 E ID_EX_MemRead $end
$var wire 5 a ID_EX_Rd [4:0] $end
$var wire 5 b IF_ID_Rs1 [4:0] $end
$var wire 5 c IF_ID_Rs2 [4:0] $end
$var wire 1 4 PCWrite $end
$var wire 1 7 IFIDWrite $end
$var reg 1 0 Stall $end
$upscope $end
$upscope $end
$upscope $end
$enddefinitions $end
$comment Show the parameter values. $end
$dumpall
$end
#0
$dumpvars
b0 c
b0 b
b0 a
b0 `
b0 _
b0 ^
b0 ]
b0 \
b0 [
b0 Z
b0 Y
b0 X
b0 W
b0 V
b0 U
b0 T
0S
b0 R
b0 Q
b0 P
b0 O
b0 N
b0 M
b0 L
b0 K
0J
b0 I
b0 H
b0 G
0F
0E
b0 D
b0 C
0B
b0 A
0@
0?
b0 >
b0 =
b0 <
b0 ;
b0 :
b0 9
b0 8
17
06
05
14
b100 3
b100 2
01
00
b0 /
b0 .
b0 -
b0 ,
b0 +
b0 *
b0 )
b0 (
b0 '
b0 &
b10000 %
b101000101000010100110011 $
b0 #
1"
0!
$end
#5000
b1 #
1!
#10000
0!
0"
#15000
11
b1000 3
b101001000010010000011 $
b110011 +
b110011 Y
b10 &
b101 )
b101 b
bx '
b1010 (
b1010 c
b1010 *
b1010 ,
b1000 2
b100 T
b101000101000010100110011 N
b10000 Q
b10 #
1!
#20000
0!
#25000
bx :
bx X
bx <
bx W
b10 =
b10 V
16
b11 +
b11 Y
bx &
b1001 )
b1001 b
b0 '
b1 (
b1 c
b1001 *
b1 ,
b1100 3
b101001010010101000100011 $
1J
b1010 L
b1010 ]
b101 K
b101 \
b1010 G
b1010 a
b1010 M
bx I
b10 H
b101001000010010000011 N
b100 O
b1100 2
b1000 T
b11 #
1!
#30000
0!
#35000
b10000 3
15
06
01
b0 <
b0 W
bx =
bx V
bx $
b100011 +
b100011 Y
b10 .
b1010 )
b1010 b
bx '
b1010 (
b1010 c
b10100 *
b1010 ,
14
17
00
bx %
b10000 2
b1100 T
b101001010010101000100011 N
b1000 O
1E
b1 L
b1 ]
b1001 K
b1001 \
b1001 G
b1001 a
b1 M
b0 I
bx H
1B
b1010 A
b1010 [
bx C
bx >
b100 #
1!
#40000
0!
#45000
bx <
bx W
05
bx /
b1 8
b1 `
b1 9
b1 _
bx +
bx Y
bx .
bx -
bx )
bx b
bx (
bx c
bx *
bx ,
b10100 3
1S
b1010 R
b1010 ^
bx P
bx Q
1?
b1001 A
b1001 [
b0 C
1F
0E
0J
b1010 L
b1010 ]
b1010 K
b1010 \
b10100 G
b10100 a
b1010 M
bx I
bx N
b1100 O
b10100 2
b10000 T
b101 #
1!
#50000
0!
#55000
b11000 3
b0 8
b0 `
b0 9
b0 _
b11000 2
b10100 T
b10000 O
0F
bx L
bx ]
bx K
bx \
bx G
bx a
bx M
1@
0?
0B
b10100 A
b10100 [
bx C
b1001 R
b1001 ^
b110 #
1!
#60000
0!
#65000
b0 /
b11100 3
0S
b10100 R
b10100 ^
0@
bx A
bx [
b10100 O
b11100 2
b11000 T
b111 #
1!
#70000
0!
#75000
b100000 3
b100000 2
b11100 T
b11000 O
bx R
bx ^
b1000 #
1!
#80000
0!
#85000
b100100 3
b11100 O
b100100 2
b100000 T
b1001 #
1!
#90000
0!
#95000
b101000 3
b101000 2
b100100 T
b100000 O
b1010 #
1!
#100000
0!
#105000
b101100 3
b100100 O
b101100 2
b101000 T
b1011 #
1!
#110000
0!
#115000
b110000 3
b110000 2
b101100 T
b101000 O
b1100 #
1!
#120000
0!
#125000
b110100 3
b101100 O
b110100 2
b110000 T
b1101 #
1!
#130000
0!
#135000
b111000 3
b111000 2
b110100 T
b110000 O
b1110 #
1!
#140000
0!
#145000
b111100 3
b110100 O
b111100 2
b111000 T
b1111 #
1!
#150000
0!
#155000
b1000000 3
b1000000 2
b111100 T
b111000 O
b10000 #
1!
#160000
0!
#165000
b1000100 3
b111100 O
b1000100 2
b1000000 T
b10001 #
1!
#170000
0!
#175000
b1001000 3
b1001000 2
b1000100 T
b1000000 O
b10010 #
1!
#180000
0!
#185000
b1001100 3
b1000100 O
b1001100 2
b1001000 T
b10011 #
1!
#190000
0!
#195000
b1010000 3
b1010000 2
b1001100 T
b1001000 O
b10100 #
1!
#200000
0!
#205000
b1010100 3
b1001100 O
b1010100 2
b1010000 T
b10101 #
1!
#210000
0!
#215000
b1011000 3
b1011000 2
b1010100 T
b1010000 O
b10110 #
1!
#220000
0!
#225000
b1011100 3
b1010100 O
b1011100 2
b1011000 T
b10111 #
1!
#230000
0!
#235000
b1100000 3
b1100000 2
b1011100 T
b1011000 O
b11000 #
1!
#240000
0!
#245000
b1100100 3
b1011100 O
b1100100 2
b1100000 T
b11001 #
1!
#250000
0!
#255000
b1101000 3
b1101000 2
b1100100 T
b1100000 O
b11010 #
1!
#260000
0!
#265000
b1101100 3
b1100100 O
b1101100 2
b1101000 T
b11011 #
1!
#270000
0!
#275000
b1110000 3
b1110000 2
b1101100 T
b1101000 O
b11100 #
1!
#280000
0!
#285000
b1110100 3
b1101100 O
b1110100 2
b1110000 T
b11101 #
1!
#290000
0!
#295000
b1111000 3
b1111000 2
b1110100 T
b1110000 O
b11110 #
1!
#300000
0!
#305000
b1111100 3
b1110100 O
b1111100 2
b1111000 T
b11111 #
1!
#310000
0!
#315000
b10000000 3
b10000000 2
b1111100 T
b1111000 O
b100000 #
1!
#320000
0!
#325000
b10000100 3
b1111100 O
b10000100 2
b10000000 T
b100001 #
1!
#330000
0!
#335000
b10001000 3
b10001000 2
b10000100 T
b10000000 O
b100010 #
1!
#340000
0!
#345000
b10001100 3
b10000100 O
b10001100 2
b10001000 T
b100011 #
1!
#350000
0!
#355000
b10010000 3
b10010000 2
b10001100 T
b10001000 O
b100100 #
1!
#360000
0!
#365000
b10010100 3
b10001100 O
b10010100 2
b10010000 T
b100101 #
1!
#370000
0!
#375000
b10011000 3
b10011000 2
b10010100 T
b10010000 O
b100110 #
1!
#380000
0!
#385000
b10011100 3
b10010100 O
b10011100 2
b10011000 T
b100111 #
1!
#390000
0!
#395000
b10100000 3
b10100000 2
b10011100 T
b10011000 O
b101000 #
1!
#400000
0!
#405000
b10100100 3
b10011100 O
b10100100 2
b10100000 T
b101001 #
1!
#410000
0!
#415000
b10101000 3
b10101000 2
b10100100 T
b10100000 O
b101010 #
1!
#420000
0!
#425000
b10101100 3
b10100100 O
b10101100 2
b10101000 T
b101011 #
1!
#430000
0!
#435000
b10110000 3
b10110000 2
b10101100 T
b10101000 O
b101100 #
1!
#440000
0!
#445000
b10110100 3
b10101100 O
b10110100 2
b10110000 T
b101101 #
1!
#450000
0!
#455000
b10111000 3
b10111000 2
b10110100 T
b10110000 O
b101110 #
1!
#460000
0!
#465000
b10111100 3
b10110100 O
b10111100 2
b10111000 T
b101111 #
1!
#470000
0!
#475000
b11000000 3
b11000000 2
b10111100 T
b10111000 O
b110000 #
1!
#480000
0!
#485000
b11000100 3
b10111100 O
b11000100 2
b11000000 T
b110001 #
1!
#490000
0!
#495000
b11001000 3
b11001000 2
b11000100 T
b11000000 O
b110010 #
1!
#500000
0!
#505000
b11001100 3
b11000100 O
b11001100 2
b11001000 T
b110011 #
1!
#510000
0!
#515000
b11010000 3
b11010000 2
b11001100 T
b11001000 O
b110100 #
1!
#520000
0!
#525000
b11010100 3
b11001100 O
b11010100 2
b11010000 T
b110101 #
1!
#530000
0!
#535000
b11011000 3
b11011000 2
b11010100 T
b11010000 O
b110110 #
1!
#540000
0!
#545000
b11011100 3
b11010100 O
b11011100 2
b11011000 T
b110111 #
1!
#550000
0!
#555000
b11100000 3
b11100000 2
b11011100 T
b11011000 O
b111000 #
1!
#560000
0!
#565000
b11100100 3
b11011100 O
b11100100 2
b11100000 T
b111001 #
1!
#570000
0!
#575000
b11101000 3
b11101000 2
b11100100 T
b11100000 O
b111010 #
1!
#580000
0!
#585000
b11101100 3
b11100100 O
b11101100 2
b11101000 T
b111011 #
1!
#590000
0!
#595000
b11110000 3
b11110000 2
b11101100 T
b11101000 O
b111100 #
1!
#600000
0!
#605000
b11110100 3
b11101100 O
b11110100 2
b11110000 T
b111101 #
1!
#610000
0!
#615000
b11111000 3
b11111000 2
b11110100 T
b11110000 O
b111110 #
1!
#620000
0!
#625000
b11111100 3
b11110100 O
b11111100 2
b11111000 T
b111111 #
1!
#630000
0!
#635000
b100000000 3
b100000000 2
b11111100 T
b11111000 O
b1000000 #
1!
#640000
0!
#645000
b100000100 3
b11111100 O
b100000100 2
b100000000 T
b1000001 #
1!
#650000
0!
#655000
b100001000 3
b100001000 2
b100000100 T
b100000000 O
b1000010 #
1!
#660000
0!
#665000
b100001100 3
b100000100 O
b100001100 2
b100001000 T
b1000011 #
1!
#670000
0!
#675000
b100010000 3
b100010000 2
b100001100 T
b100001000 O
b1000100 #
1!
#680000
0!
#685000
b100010100 3
b100001100 O
b100010100 2
b100010000 T
b1000101 #
1!
#690000
0!
#695000
b100011000 3
b100011000 2
b100010100 T
b100010000 O
b1000110 #
1!
#700000
0!
#705000
b100011100 3
b100010100 O
b100011100 2
b100011000 T
b1000111 #
1!
#710000
0!
#715000
b100100000 3
b100100000 2
b100011100 T
b100011000 O
b1001000 #
1!
#720000
0!
#725000
b100100100 3
b100011100 O
b100100100 2
b100100000 T
b1001001 #
1!
#730000
0!
#735000
b100101000 3
b100101000 2
b100100100 T
b100100000 O
b1001010 #
1!
#740000
0!
#745000
b100101100 3
b100100100 O
b100101100 2
b100101000 T
b1001011 #
1!
#750000
0!
#755000
b100110000 3
b100110000 2
b100101100 T
b100101000 O
b1001100 #
1!
#760000
0!
#765000
b100110100 3
b100101100 O
b100110100 2
b100110000 T
b1001101 #
1!
#770000
0!
#775000
b100111000 3
b100111000 2
b100110100 T
b100110000 O
b1001110 #
1!
#780000
0!
#785000
b100111100 3
b100110100 O
b100111100 2
b100111000 T
b1001111 #
1!
#790000
0!
#795000
b101000000 3
b101000000 2
b100111100 T
b100111000 O
b1010000 #
1!
#800000
0!
#805000
b101000100 3
b100111100 O
b101000100 2
b101000000 T
b1010001 #
1!
#810000
0!
#815000
b101001000 3
b101001000 2
b101000100 T
b101000000 O
b1010010 #
1!
#820000
0!
#825000
b101001100 3
b101000100 O
b101001100 2
b101001000 T
b1010011 #
1!
#830000
0!
#835000
b101010000 3
b101010000 2
b101001100 T
b101001000 O
b1010100 #
1!
#840000
0!
#845000
b101010100 3
b101001100 O
b101010100 2
b101010000 T
b1010101 #
1!
#850000
0!
#855000
b101011000 3
b101011000 2
b101010100 T
b101010000 O
b1010110 #
1!
#860000
0!
#865000
b101011100 3
b101010100 O
b101011100 2
b101011000 T
b1010111 #
1!
#870000
0!
#875000
b101100000 3
b101100000 2
b101011100 T
b101011000 O
b1011000 #
1!
#880000
0!
#885000
b101100100 3
b101011100 O
b101100100 2
b101100000 T
b1011001 #
1!
#890000
0!
#895000
b101101000 3
b101101000 2
b101100100 T
b101100000 O
b1011010 #
1!
#900000
0!
#905000
b101101100 3
b101100100 O
b101101100 2
b101101000 T
b1011011 #
1!
#910000
0!
#915000
b101110000 3
b101110000 2
b101101100 T
b101101000 O
b1011100 #
1!
#920000
0!
#925000
b101110100 3
b101101100 O
b101110100 2
b101110000 T
b1011101 #
1!
#930000
0!
#935000
b101111000 3
b101111000 2
b101110100 T
b101110000 O
b1011110 #
1!
#940000
0!
#945000
b101111100 3
b101110100 O
b101111100 2
b101111000 T
b1011111 #
1!
#950000
0!
#955000
b110000000 3
b110000000 2
b101111100 T
b101111000 O
b1100000 #
1!
#960000
0!
#965000
b110000100 3
b101111100 O
b110000100 2
b110000000 T
b1100001 #
1!
#970000
0!
#975000
b110001000 3
b110001000 2
b110000100 T
b110000000 O
b1100010 #
1!
#980000
0!
#985000
b110001100 3
b110000100 O
b110001100 2
b110001000 T
b1100011 #
1!
